{
  "nid": "322734",
  "title": "오설록, 설 맞이 선물 프로모션 진행",
  "content": "오설록이 설을 맞아 티 세트와 명절 선물 수요에 맞춘 다채로운 프로모션을 진행한다. ⓒ아모레퍼시픽오설록이 설을 맞아 티 세트와 명절 선물 수요에 맞춘 다채로운 프로모션을 진행한다고 3일 밝혔다.오설록 직영몰에서는 구매 금액대별 쿠폰팩과 요일별 타임딜 등 다양한 온라인 전용 혜택을 제공한다. 매주 월·수·금요일에 진행하는 ‘하루 특가 타임딜’을 통해 베스트 티 세트와 조합 세트를 최대 45% 할인된 가격으로 만나볼 수 있다.특히 대표 프리미엄 세트인 ‘티 에디션 헤리티지’와 ‘티 에디션 스페셜’은 은은한 비침이 특징인 노방 보자기 포장이 더해져 고급스러움을 완성했다.전국 오설록 티하우스와 백화점 티샵에서는 주요 선물 세트 할인과 함께 오프라인 전용 프로모션을 선보인다. 구매 금액별로 설날 트라이얼 키트를 증정하고, 한복 가방 1만 원 구매 기회를 제공한다.한복 가방은 청록색 양단 원단에 2026년 말의 해를 상징하는 자수를 더해 실용적인 크기와 고급스러운 디테일을 갖춰 명절 선물의 특별함을 더했다.‘도약하는 새해의 기운을 담아, 정성으로 전하는 설 인사’ 테마로 진행하는 이번 프로모션은 3일부터 18일까지 오설록 직영몰과 전국 오프라인 매장에서 만나볼 수 있다.",
  "author": "김민혜 기자",
  "email": "minyang@yakup.com",
  "category": "산업",
  "published_at": "2026.02.03 10:29",
  "url": "https://www.yakup.com/news/index.html?mode=view&cat=12&nid=322734",
  "scraped_at": "2026-02-03T11:16:54.408693"
}